louati_cli/__init__.py
louati_cli/ascii_art.py
louati_cli/cli.py
louati_cli/data.py
louati_cli/utils.py
louati_cli-0.1.0.dist-info/METADATA
louati_cli-0.1.0.dist-info/WHEEL
louati_cli-0.1.0.dist-info/entry_points.txt
louati_cli-0.1.0.dist-info/top_level.txt
louati_cli-0.1.0.dist-info/RECORD
