Metadata-Version: 2.4
Name: louati-cli
Version: 0.1.0
Summary: Interactive CLI to explore Louati Mahdi's data engineering expertise
Home-page: https://github.com/mahdi123-tech
Author: Louati Mahdi
Author-email: louatimahdi390@gmail.com
Classifier: Programming Language :: Python :: 3
Classifier: License :: OSI Approved :: MIT License
Classifier: Operating System :: OS Independent
Classifier: Topic :: Terminals
Requires-Python: >=3.8
Requires-Dist: click>=8.1.3
Requires-Dist: termcolor>=2.3.0
Requires-Dist: pyfiglet>=0.8.post1
Requires-Dist: yaspin>=2.2.0
Dynamic: author
Dynamic: author-email
Dynamic: classifier
Dynamic: description
Dynamic: description-content-type
Dynamic: home-page
Dynamic: requires-dist
Dynamic: requires-python
Dynamic: summary
